libuseful-0.4.7.dist-info/LICENSE
libuseful-0.4.7.dist-info/METADATA
libuseful-0.4.7.dist-info/RECORD
libuseful-0.4.7.dist-info/WHEEL
libuseful/__init__.pyc
libuseful/__init__.pyi
libuseful/exception.pyc
libuseful/exception.pyi
libuseful/lib_adb.pyc
libuseful/lib_adb.pyi
libuseful/lib_args.pyc
libuseful/lib_args.pyi
libuseful/lib_async_loop.pyc
libuseful/lib_async_loop.pyi
libuseful/lib_cam_record.pyc
libuseful/lib_cam_record.pyi
libuseful/lib_dynamic_import.pyc
libuseful/lib_dynamic_import.pyi
libuseful/lib_enum.pyc
libuseful/lib_enum.pyi
libuseful/lib_excel.pyc
libuseful/lib_excel.pyi
libuseful/lib_fatal.pyc
libuseful/lib_fatal.pyi
libuseful/lib_file.pyc
libuseful/lib_file.pyi
libuseful/lib_logger.pyc
libuseful/lib_logger.pyi
libuseful/lib_math_geometry.pyc
libuseful/lib_math_geometry.pyi
libuseful/lib_path.pyc
libuseful/lib_path.pyi
libuseful/lib_path_remote_linux.pyc
libuseful/lib_path_remote_linux.pyi
libuseful/lib_processor.pyc
libuseful/lib_processor.pyi
libuseful/lib_ps.pyc
libuseful/lib_ps.pyi
libuseful/lib_retry.pyc
libuseful/lib_retry.pyi
libuseful/lib_shell.pyc
libuseful/lib_shell.pyi
libuseful/lib_shell_raw.pyc
libuseful/lib_shell_raw.pyi
libuseful/lib_singleton.pyc
libuseful/lib_singleton.pyi
libuseful/lib_thread.pyc
libuseful/lib_thread.pyi
libuseful/lib_threadsM.pyc
libuseful/lib_threadsM.pyi
libuseful/lib_time.pyc
libuseful/lib_time.pyi
libuseful/lib_usermng.pyc
libuseful/lib_usermng.pyi
libuseful/lib_watchdog.pyc
libuseful/lib_watchdog.pyi
