Metadata-Version: 2.1
Name: libuseful
Version: 0.4.7
Summary: It's useful library, commonly.\n(path/file/shell/thread/process/watchdog/async/args/logger/retry/singleton/time/cam/dynamic_import/excel/geometry_math/user_mng)
License: MIT
Keywords: libuseful,useful,library,common-lib,util
Author: Irradiance
Author-email: irradiance.hong@gmail.com
Requires-Python: >=3.8,<4.0
Classifier: License :: OSI Approved :: MIT License
Classifier: Operating System :: Microsoft :: Windows :: Windows 10
Classifier: Operating System :: POSIX :: Linux
Classifier: Programming Language :: Python :: 3
Classifier: Programming Language :: Python :: 3.8
Classifier: Programming Language :: Python :: 3.9
Classifier: Programming Language :: Python :: 3.10
Classifier: Programming Language :: Python :: 3.11
Classifier: Programming Language :: Python :: 3.12
Classifier: Programming Language :: Python :: 3.13
Classifier: Topic :: Software Development :: Libraries :: Python Modules
Classifier: Topic :: Utilities
Requires-Dist: chardet (>=5.2.0,<6.0.0)
Requires-Dist: numpy (==1.24.4)
Requires-Dist: opencv-python (==4.8.1.78)
Requires-Dist: openpyxl (>=3.1.5,<4.0.0)
Requires-Dist: pandas (==2.0.3)
Requires-Dist: psutil (>=6.1.0,<7.0.0)
Requires-Dist: pure-python-adb (==0.3.*)
Requires-Dist: python-dateutil (>=2.9.0.post0,<3.0.0)
Requires-Dist: retry (>=0.9.2,<0.10.0)
